SimuBox/__init__.py
SimuBox/artist/__init__.py
SimuBox/artist/compare.py
SimuBox/artist/isosurface.py
SimuBox/artist/landscape.py
SimuBox/artist/phase.py
SimuBox/artist/plotter.py
SimuBox/calculator/__init__.py
SimuBox/calculator/peak.py
SimuBox/calculator/scatter.py
SimuBox/calculator/topo.py
SimuBox/calculator/voronoi.py
SimuBox/runner/__init__.py
SimuBox/runner/agents/__init__.py
SimuBox/runner/agents/ABC.py
SimuBox/runner/agents/ABC_ABC.py
SimuBox/runner/agents/BABCB.py
SimuBox/runner/agents/Mask_AB_A.py
SimuBox/runner/agents/Mask_AB_AB.py
SimuBox/runner/agents/MixinModel.py
SimuBox/runner/manager.py
SimuBox/runner/phases.py
SimuBox/schema/__init__.py
SimuBox/schema/enums/__init__.py
SimuBox/schema/enums/MixinEnums.py
SimuBox/schema/enums/Modes.py
SimuBox/schema/enums/OtherEnums.py
SimuBox/schema/enums/SCFTEnums.py
SimuBox/schema/labels.py
SimuBox/schema/structs/__init__.py
SimuBox/schema/structs/ChartElement.py
SimuBox/schema/structs/ComputedRes.py
SimuBox/schema/structs/DataFile.py
SimuBox/schema/structs/MixinStructs.py
SimuBox/schema/structs/OtherStructs.py
SimuBox/schema/structs/SCFTStructs.py
SimuBox/schema/types.py
SimuBox/script/extractor.py
SimuBox/script/help.py
SimuBox/script/JSON/ABC_ABC.json
SimuBox/script/JSON/BABCB.json
SimuBox/script/push_job.py
SimuBox/script/setenv.py
SimuBox/script/stress.py
SimuBox/script/transform_case.py
SimuBox/script/web.py
SimuBox/toolkit/__init__.py
SimuBox/toolkit/function.py
SimuBox/toolkit/reader.py
SimuBox/toolkit/vector.py
SimuBox/toolkit/xmltrans.py
SimuBox/web/Homepage.py
SimuBox/web/pages/1_Structure.py
SimuBox/web/pages/2_Scatter.py
SimuBox/web/pages/3_Voronoi.py
SimuBox/web/pages/4_Curve.py
SimuBox/web/pages/5_Peaks.py
SimuBox/web/pages/6_Topology.py
SimuBox/web/pages/7_Landscape.py
simubox-0.2.6.dist-info/LICENSE
simubox-0.2.6.dist-info/METADATA
simubox-0.2.6.dist-info/WHEEL
simubox-0.2.6.dist-info/RECORD
