Metadata-Version: 2.1
Name: SimuBox
Version: 0.2.6
Summary: Free python package to do some science calculation.
Home-page: https://pypi.org/project/SimuBox/
License: ./LICENSE
Author: Alkaid Yuan
Author-email: kryuan@qq.com
Maintainer: Alkaid Yuan
Maintainer-email: kryuan@qq.com
Requires-Python: >=3.10,<4.0
Classifier: License :: Other/Proprietary License
Classifier: Programming Language :: Python :: 3
Classifier: Programming Language :: Python :: 3.10
Classifier: Programming Language :: Python :: 3.11
Classifier: Programming Language :: Python :: 3.12
Requires-Dist: matplotlib (>=3.8.2,<4.0.0)
Requires-Dist: numpy (>=1.26.2,<2.0.0)
Requires-Dist: opencv-python (>=4.8.1.78,<5.0.0.0)
Requires-Dist: opencv-python-headless (>=4.8.1.78,<5.0.0.0)
Requires-Dist: pandas (>=2.1.4,<3.0.0)
Requires-Dist: plotly (>=5.20.0,<6.0.0)
Requires-Dist: poetry-plugin-export (>=1.6.0,<2.0.0)
Requires-Dist: pydantic (>=2.5.2,<3.0.0)
Requires-Dist: pyecharts (>=2.0.5,<3.0.0)
Requires-Dist: pyvista (>=0.43.1,<0.44.0)
Requires-Dist: scikit-image (>=0.22.0,<0.23.0)
Requires-Dist: scikit-learn (>=1.3.2,<2.0.0)
Requires-Dist: scipy (>=1.11.4,<2.0.0)
Requires-Dist: shapely (>=2.0.2,<3.0.0)
Requires-Dist: simplejson (>=3.19.2,<4.0.0)
Requires-Dist: stpyvista (>=0.0.11,<0.0.12)
Requires-Dist: streamlit (>=1.29.0,<2.0.0)
Requires-Dist: streamlit-extras (>=0.3.6,<0.4.0)
Requires-Dist: streamlit-nested-layout (>=0.1.1,<0.2.0)
Requires-Dist: sympy (>=1.12,<2.0)
Requires-Dist: tqdm (>=4.66.1,<5.0.0)
Project-URL: Repository, https://github.com/KangruiYuan/SimuBox
